ChangeLog
LICENSE.txt
MANIFEST.in
Makefile
README.md
decl.pxd
isr84lib.cc
isr84lib.h
itm.cpp
itm.pyx
setup.py
test_itm.py
itm.egg-info/PKG-INFO
itm.egg-info/SOURCES.txt
itm.egg-info/dependency_links.txt
itm.egg-info/top_level.txt